.gitignore
LICENSE
MANIFEST.in
README.md
equation.svg
inplace_abn.png
licenses.csv
requirements.txt
setup.cfg
setup.py
include/checks.h
include/cuda_utils.cuh
include/dispatch.h
include/inplace_abn.h
include/utils.h
inplace_abn/__init__.py
inplace_abn/_backend.pyi
inplace_abn/_version.py
inplace_abn/abn.py
inplace_abn/functions.py
inplace_abn/group.py
inplace_abn.egg-info/PKG-INFO
inplace_abn.egg-info/SOURCES.txt
inplace_abn.egg-info/dependency_links.txt
inplace_abn.egg-info/top_level.txt
scripts/requirements.txt
scripts/test_imagenet.py
scripts/test_vistas.py
scripts/test_vistas_single_gpu.py
scripts/train_imagenet.py
scripts/dataset/__init__.py
scripts/dataset/dataset.py
scripts/dataset/sampler.py
scripts/dataset/transform.py
scripts/experiments/densenet264_ipabn_lr_256.json
scripts/experiments/resnet101_ipabn-sync_lr_512.json
scripts/experiments/resnet34_ipabn-sync_lr_512.json
scripts/experiments/resnet50_ipabn-sync_lr_512.json
scripts/experiments/resnext101_ipabn-sync_lr_256.json
scripts/experiments/resnext101_ipabn_lr_512.json
scripts/experiments/resnext101_stdbn_lr_256.json
scripts/experiments/resnext152_ipabn_lr_256.json
scripts/experiments/wider_resnet38_ipabn_lr_256.json
scripts/imagenet/__init__.py
scripts/imagenet/config.py
scripts/imagenet/transforms.py
scripts/imagenet/utils.py
scripts/models/__init__.py
scripts/models/densenet.py
scripts/models/resnet.py
scripts/models/resnext.py
scripts/models/util.py
scripts/models/wider_resnet.py
scripts/modules/__init__.py
scripts/modules/deeplab.py
scripts/modules/dense.py
scripts/modules/misc.py
scripts/modules/residual.py
src/inplace_abn.cpp
src/inplace_abn_cpu.cpp
src/inplace_abn_cuda.cu
src/inplace_abn_kernels.cuh
src/utils.cpp