Metadata-Version: 2.1
Name: inplace-abn
Version: 1.0.11
Summary: In-Place Activate BatchNorm for Pytorch
Home-page: https://github.com/mapillary/inplace_abn
Author: Lorenzo Porzi
Author-email: lorenzo@mapillary.com
License: UNKNOWN
Platform: UNKNOWN
Classifier: Programming Language :: Python :: 3
Classifier: Programming Language :: Python :: 3.4
Classifier: Programming Language :: Python :: 3.5
Classifier: Programming Language :: Python :: 3.6
Classifier: Programming Language :: Python :: 3.7
Requires-Python: >=3, <4
